{
  "name": "Alena",
  "city": "Москва",
  "category": "Piercing",
  "telegram": "@alena_piercing",
  "instagram": "@alena_piercing_studio",
  "tiktok": "@alena_piercing",
  "pinterest": "alena_piercing_studio",
  "pinterestUrl": "https://pinterest.com/alena_piercing_studio",
  "telegramUrl": "https://t.me/alena_piercing",
  "tiktokUrl": "https://tiktok.com/@alena_piercing",
  "bookingUrl": "https://t.me/alena_piercing",
  "locationHtml": "Москва, м. Арбатская<br>Студия \"Alena Piercing\"",
  "galleryHtml": "Галерея пирсингов и украшений"
} 